pbi_mermaid/__init__.py
pbi_mermaid/diagram.py
pbi_mermaid/link.py
pbi_mermaid/node.py
pbi_mermaid/browser/__init__.py
pbi_mermaid/browser/legend.html
pbi_mermaid/browser/main.py
pbi_mermaid/browser/template_advanced.html
pbi_mermaid/browser/template_simple.html
pbi_mermaid/misc/__init__.py
pbi_mermaid/misc/chunker.py
pbi_mermaid-0.4.0.dist-info/METADATA
pbi_mermaid-0.4.0.dist-info/WHEEL
pbi_mermaid-0.4.0.dist-info/licenses/LICENSE
pbi_mermaid-0.4.0.dist-info/RECORD
